README.rst
setup.cfg
setup.py
pelican_do/__init__.py
pelican_do/main.py
pelican_do/post.py
pelican_do.egg-info/PKG-INFO
pelican_do.egg-info/SOURCES.txt
pelican_do.egg-info/dependency_links.txt
pelican_do.egg-info/entry_points.txt
pelican_do.egg-info/requires.txt
pelican_do.egg-info/top_level.txt
pelican_do/utils/__init__.py
pelican_do/utils/filters.py
tests/__init__.py
tests/test_pelican_do.py
tests/test_post.py